IdeaLib/__init__.py
IdeaLib-0.2.0.dist-info/METADATA
IdeaLib-0.2.0.dist-info/WHEEL
IdeaLib-0.2.0.dist-info/top_level.txt
IdeaLib-0.2.0.dist-info/RECORD
